django_camunda/__init__.py
django_camunda/admin.py
django_camunda/api.py
django_camunda/apps.py
django_camunda/bpmn.py
django_camunda/camunda_models.py
django_camunda/client.py
django_camunda/constants.py
django_camunda/fields.py
django_camunda/forms.py
django_camunda/interface.py
django_camunda/models.py
django_camunda/py.typed
django_camunda/tasks.py
django_camunda/types.py
django_camunda/utils.py
django_camunda/dmn/__init__.py
django_camunda/dmn/api.py
django_camunda/dmn/datastructures.py
django_camunda/dmn/parser.py
django_camunda/management/__init__.py
django_camunda/management/commands/__init__.py
django_camunda/management/commands/delete_process_instance.py
django_camunda/migrations/0001_initial.py
django_camunda/migrations/0002_camundaconfig_auth_header.py
django_camunda/migrations/0003_auto_20200227_1552.py
django_camunda/migrations/0004_camundaconfig_enabled.py
django_camunda/migrations/0005_auto_20211220_1742.py
django_camunda/migrations/__init__.py
django_camunda-0.15.1.dist-info/licenses/LICENSE
tests/dmn/__init__.py
tests/dmn/test_evaluation.py
tests/dmn/test_parser.py
django_camunda-0.15.1.dist-info/METADATA
django_camunda-0.15.1.dist-info/WHEEL
django_camunda-0.15.1.dist-info/top_level.txt
django_camunda-0.15.1.dist-info/RECORD
