Metadata-Version: 2.4
Name: django-camunda
Version: 0.15.1
Summary: Interact with Camunda from Django
Home-page: https://github.com/maykinmedia/django-camunda
Author: Maykin Media
Author-email: support@maykinmedia.nl
License: MIT
Keywords: camunda,process engine,bpmn,common ground
Classifier: Development Status :: 3 - Alpha
Classifier: Framework :: Django
Classifier: Framework :: Django :: 4.2
Classifier: Framework :: Django :: 5.0
Classifier: Intended Audience :: Developers
Classifier: Operating System :: Unix
Classifier: Operating System :: MacOS
Classifier: Operating System :: Microsoft :: Windows
Classifier: Programming Language :: Python :: 3.10
Classifier: Programming Language :: Python :: 3.11
Classifier: Programming Language :: Python :: 3.12
Classifier: Topic :: Software Development :: Libraries :: Python Modules
Requires-Python: >=3.10
License-File: LICENSE
Requires-Dist: lxml
Requires-Dist: django>=4.2
Requires-Dist: django-solo
Requires-Dist: inflection
Requires-Dist: requests
Requires-Dist: python-dateutil
Provides-Extra: celery
Requires-Dist: celery; extra == "celery"
Provides-Extra: tests
Requires-Dist: pytest; extra == "tests"
Requires-Dist: pytest-django; extra == "tests"
Requires-Dist: requests_mock; extra == "tests"
Requires-Dist: django-webtest; extra == "tests"
Requires-Dist: tox; extra == "tests"
Requires-Dist: isort; extra == "tests"
Requires-Dist: black; extra == "tests"
Provides-Extra: coverage
Requires-Dist: pytest-cov; extra == "coverage"
Provides-Extra: docs
Requires-Dist: sphinx; extra == "docs"
Requires-Dist: sphinx-rtd-theme; extra == "docs"
Provides-Extra: release
Requires-Dist: bumpversion; extra == "release"
Requires-Dist: twine; extra == "release"
Dynamic: license-file
